{
  "contacts": [
    {
      "letter": "A",
      "people": [
        {
          "id": 1,
          "name": "Angelina Jackson",
          "phone": "(415) 053-8702",
          "b_day": "4 / 19 / 1998"
        },
        {
          "id": 2,
          "name": "Alex Davis",
          "phone": "(415) 027-9034",
          "b_day": "7 / 3 / 2001"
        }
      ]
    },
    {
      "letter": "B",
      "people": [
        {
          "id": 3,
          "name": "Betty Hamilton",
          "phone": "(415) 084-2861",
          "b_day": "10 / 23 / 1993"
        },
        {
          "id": 4,
          "name": "Becca Smith",
          "phone": "(415) 051-6253",
          "b_day": "2 / 17 / 1996"
        },
        {
          "id": 5,
          "name": "Bruce Williams",
          "phone": "(415) 094-7104",
          "b_day": "5 / 29 / 1997"
        }
      ]
    }
  ]
}
